splashpaper.py
splashpaper-1.3.4.dist-info/LICENSE
splashpaper-1.3.4.dist-info/WHEEL
splashpaper-1.3.4.dist-info/METADATA
splashpaper-1.3.4.dist-info/RECORD
