Metadata-Version: 2.1
Name: splashpaper
Version: 1.3.4
Summary: Wallpaper manager with unsplash.com integration
Home-page: https://github.com/evtn/splashpaper
License: MIT
Author: Dmitry Gritsenko
Author-email: splashpaper@evtn.ru
Requires-Python: >=3.6,<4.0
Classifier: License :: OSI Approved :: MIT License
Classifier: Programming Language :: Python :: 3
Classifier: Programming Language :: Python :: 3.10
Classifier: Programming Language :: Python :: 3.6
Classifier: Programming Language :: Python :: 3.7
Classifier: Programming Language :: Python :: 3.8
Classifier: Programming Language :: Python :: 3.9
Requires-Dist: requests (>=2.28.1,<3.0.0)
Project-URL: Repository, https://github.com/evtn/splashpaper
